setup.cfg
setup.py
nltk_punkt/__init__.py
nltk_punkt/main.py
nltk_punkt.egg-info/PKG-INFO
nltk_punkt.egg-info/SOURCES.txt
nltk_punkt.egg-info/dependency_links.txt
nltk_punkt.egg-info/requires.txt
nltk_punkt.egg-info/top_level.txt